LICENSE.txt
MANIFEST.in
README.rst
setup.cfg
setup.py
rq_scheduler/__init__.py
rq_scheduler/scheduler.py
rq_scheduler/utils.py
rq_scheduler/scripts/__init__.py
rq_scheduler/scripts/rqscheduler.py
rq_scheduler_bcfg.egg-info/PKG-INFO
rq_scheduler_bcfg.egg-info/SOURCES.txt
rq_scheduler_bcfg.egg-info/dependency_links.txt
rq_scheduler_bcfg.egg-info/entry_points.txt
rq_scheduler_bcfg.egg-info/not-zip-safe
rq_scheduler_bcfg.egg-info/requires.txt
rq_scheduler_bcfg.egg-info/top_level.txt